MANIFEST.in
README.md
pyproject.toml
setup.py
omuse_swan.egg-info/PKG-INFO
omuse_swan.egg-info/SOURCES.txt
omuse_swan.egg-info/dependency_links.txt
omuse_swan.egg-info/requires.txt
omuse_swan.egg-info/top_level.txt
src/omuse/community/swan/Makefile
src/omuse/community/swan/__init__.py
src/omuse/community/swan/interface.f90
src/omuse/community/swan/interface.py
src/omuse/community/swan/swaninit
src/omuse/community/swan/version.py
src/omuse/community/swan/src/Makefile
src/omuse/community/swan/src/amuse_swan.ftn90
src/omuse/community/swan/src/macros.inc
src/omuse/community/swan/src/swan.patch
src/omuse/community/swan/src/swan/HottifySWAN.ftn90
src/omuse/community/swan/src/swan/INSTALL.README
src/omuse/community/swan/src/swan/Makefile
src/omuse/community/swan/src/swan/SWANRUN.README
src/omuse/community/swan/src/swan/SwanBndStruc.ftn90
src/omuse/community/swan/src/swan/SwanBpntlist.ftn90
src/omuse/community/swan/src/swan/SwanCheckGrid.ftn90
src/omuse/community/swan/src/swan/SwanCompUnstruc.ftn90
src/omuse/community/swan/src/swan/SwanCompdata.ftn90
src/omuse/community/swan/src/swan/SwanComputeForce.ftn90
src/omuse/community/swan/src/swan/SwanConvAccur.ftn90
src/omuse/community/swan/src/swan/SwanConvStopc.ftn90
src/omuse/community/swan/src/swan/SwanCreateEdges.ftn90
src/omuse/community/swan/src/swan/SwanCrossObstacle.ftn90
src/omuse/community/swan/src/swan/SwanDiffPar.ftn90
src/omuse/community/swan/src/swan/SwanDispParm.ftn90
src/omuse/community/swan/src/swan/SwanFindObstacles.ftn90
src/omuse/community/swan/src/swan/SwanFindPoint.ftn90
src/omuse/community/swan/src/swan/SwanGSECorr.ftn90
src/omuse/community/swan/src/swan/SwanGridCell.ftn90
src/omuse/community/swan/src/swan/SwanGridFace.ftn90
src/omuse/community/swan/src/swan/SwanGridTopology.ftn90
src/omuse/community/swan/src/swan/SwanGridVert.ftn90
src/omuse/community/swan/src/swan/SwanGriddata.ftn90
src/omuse/community/swan/src/swan/SwanGridobjects.ftn90
src/omuse/community/swan/src/swan/SwanInitCompGrid.ftn90
src/omuse/community/swan/src/swan/SwanInterpolateAc.ftn90
src/omuse/community/swan/src/swan/SwanInterpolateOutput.ftn90
